django_openai_assistant/.DS_Store
django_openai_assistant/__init__.py
django_openai_assistant/apps.py
django_openai_assistant/assistant.py
django_openai_assistant/models.py
django_openai_assistant/migrations/0001_initial.py
django_openai_assistant/migrations/__init__.py
django_openai_assistant-0.33.dist-info/METADATA
django_openai_assistant-0.33.dist-info/WHEEL
django_openai_assistant-0.33.dist-info/licenses/LICENSE
django_openai_assistant-0.33.dist-info/RECORD
