Metadata-Version: 2.1
Name: django-openai-assistant
Version: 0.33
Summary: Django OpenAI Assistant
Project-URL: Homepage, https://github.com/jlvanhulst/django-openai
Author-email: Jean-Luc Vanhulst <jl@valor.vc>
Maintainer-email: Jean-Luc Vanhulst <jl@valor.vc>
License-File: LICENSE
Keywords: assistants,celery,django,openai
Classifier: License :: OSI Approved :: MIT License
Requires-Dist: markdown
Requires-Dist: openai
